LICENSE
README.md
setup.py
protod/__init__.py
protod/decode.py
protod/definition.py
protod/field.py
protod/main.py
protod/renderer.py
protod/util.py
protod.egg-info/PKG-INFO
protod.egg-info/SOURCES.txt
protod.egg-info/dependency_links.txt
protod.egg-info/entry_points.txt
protod.egg-info/requires.txt
protod.egg-info/top_level.txt