Metadata-Version: 2.1
Name: protod
Version: 24.2.1
Summary: Decode protobuf without message definition.
Home-page: https://github.com/aj3423/protod/
Author: aj3423
License-File: LICENSE
